odoo/addons/pos_timeout/README.rst
odoo/addons/pos_timeout/__init__.py
odoo/addons/pos_timeout/__manifest__.py
odoo/addons/pos_timeout/i18n/ca.po
odoo/addons/pos_timeout/i18n/es.po
odoo/addons/pos_timeout/i18n/fr.po
odoo/addons/pos_timeout/i18n/hr_HR.po
odoo/addons/pos_timeout/i18n/it.po
odoo/addons/pos_timeout/i18n/nl_NL.po
odoo/addons/pos_timeout/i18n/pos_timeout.pot
odoo/addons/pos_timeout/models/__init__.py
odoo/addons/pos_timeout/models/pos_config.py
odoo/addons/pos_timeout/models/res_config_settings.py
odoo/addons/pos_timeout/readme/CONFIGURE.rst
odoo/addons/pos_timeout/readme/CONTRIBUTORS.rst
odoo/addons/pos_timeout/readme/CREDITS.rst
odoo/addons/pos_timeout/readme/DESCRIPTION.rst
odoo/addons/pos_timeout/static/description/icon.png
odoo/addons/pos_timeout/static/description/index.html
odoo/addons/pos_timeout/static/description/pos_config.png
odoo/addons/pos_timeout/static/src/js/models.js
odoo/addons/pos_timeout/views/res_config_settings.xml
odoo_addon_pos_timeout-16.0.1.0.0.4.dist-info/METADATA
odoo_addon_pos_timeout-16.0.1.0.0.4.dist-info/WHEEL
odoo_addon_pos_timeout-16.0.1.0.0.4.dist-info/top_level.txt
odoo_addon_pos_timeout-16.0.1.0.0.4.dist-info/RECORD
